pyd_xml/__init__.py
pyd_xml/base.py
pyd_xml/decoder.py
pyd_xml/encoder.py
pyd_xml/exceptions.py
pyd_xml/fields.py
pyd_xml/py.typed
pyd_xml/utils.py
pyd_xml-0.1.0.dist-info/licenses/LICENSE
pyd_xml-0.1.0.dist-info/METADATA
pyd_xml-0.1.0.dist-info/WHEEL
pyd_xml-0.1.0.dist-info/top_level.txt
pyd_xml-0.1.0.dist-info/RECORD
