Metadata-Version: 2.4
Name: pyd-xml
Version: 0.1.0
Summary: Easily serialize Pydantic models to and from XML.
Author-email: Mohamed Tahri <simotahri1@gmail.com>
License:                                  Apache License
Project-URL: Homepage, https://github.com/metahris/pyd-xml
Project-URL: Repository, https://github.com/metahris/pyd-xml
Project-URL: Documentation, https://github.com/metahris/pyd-xml#readme
Project-URL: Issues, https://github.com/metahris/pyd-xml/issues
Project-URL: Changelog, https://github.com/metahris/pyd-xml/releases
Keywords: pydantic,xml,serialization,deserialization,parser
Classifier: Development Status :: 4 - Beta
Classifier: Intended Audience :: Developers
Classifier: Topic :: Software Development :: Libraries
Classifier: Topic :: Text Processing :: Markup :: XML
Classifier: Programming Language :: Python :: 3
Classifier: Programming Language :: Python :: 3.9
Classifier: Programming Language :: Python :: 3.10
Classifier: Programming Language :: Python :: 3.11
Classifier: License :: OSI Approved :: MIT License
Requires-Python: >=3.10
License-File: LICENSE
Requires-Dist: pydantic<3.0,>=2.0
Requires-Dist: lxml>=4.9
Provides-Extra: dev
Requires-Dist: pytest>=7.0; extra == "dev"
Requires-Dist: mypy>=1.0; extra == "dev"
Requires-Dist: black>=23.0; extra == "dev"
Requires-Dist: ruff>=0.1.0; extra == "dev"
Provides-Extra: all
Requires-Dist: pydantic<3.0,>=2.0; extra == "all"
Requires-Dist: lxml>=4.9; extra == "all"
Dynamic: license-file
